loguru_wrapper/__init__.py
loguru_wrapper/loguru_config.py
loguru_wrapper/main.py
loguru_wrapper/wrapper.py
loguru_wrapper-0.3.0.dist-info/METADATA
loguru_wrapper-0.3.0.dist-info/WHEEL
loguru_wrapper-0.3.0.dist-info/top_level.txt
loguru_wrapper-0.3.0.dist-info/RECORD
