Metadata-Version: 2.4
Name: loguru_wrapper
Version: 0.3.0
Author-email: Joni Töyrylä <info@jonitoyryla.eu>
License-Expression: MIT
Project-URL: Source, https://github.com/Nerdman4U/loguru_wrapper
Classifier: Intended Audience :: Developers
Classifier: Programming Language :: Python :: 3
Classifier: Development Status :: 4 - Beta
Requires-Python: >=3.10
Requires-Dist: loguru>=0.7.3
Requires-Dist: stackwalker>=0.4.2
